[{"Produkt_ID":9,"Verkaufte Menge":272,"Produkt_Name":"Hela Gewuerz Ketchup Mild","Preis pro St\u00fcck":1.99,"Umsatz":541.28},{"Produkt_ID":26,"Verkaufte Menge":351,"Produkt_Name":"Sierra Tequila Reposado 0,7L","Preis pro St\u00fcck":15.99,"Umsatz":5612.49},{"Produkt_ID":33,"Verkaufte Menge":436,"Produkt_Name":"Bifi Original 6ST 120G","Preis pro St\u00fcck":3.29,"Umsatz":1434.44},{"Produkt_ID":32,"Verkaufte Menge":399,"Produkt_Name":"Milkana Sahne 190G","Preis pro St\u00fcck":2.99,"Umsatz":1193.01},{"Produkt_ID":17,"Verkaufte Menge":388,"Produkt_Name":"Salzstangen 250G","Preis pro St\u00fcck":2.29,"Umsatz":888.52},{"Produkt_ID":18,"Verkaufte Menge":412,"Produkt_Name":"Fanta Orange 4x 0,5L PET","Preis pro St\u00fcck":4.99,"Umsatz":2055.88},{"Produkt_ID":22,"Verkaufte Menge":264,"Produkt_Name":"Monster Energydrink The Doctor 0,5L","Preis pro St\u00fcck":1.59,"Umsatz":419.76},{"Produkt_ID":11,"Verkaufte Menge":350,"Produkt_Name":"Vitrex Mineralwasser Medium 6x 0,5L","Preis pro St\u00fcck":1.89,"Umsatz":661.5},{"Produkt_ID":24,"Verkaufte Menge":336,"Produkt_Name":"Rotkaeppchen Sekt mild 0,75L","Preis pro St\u00fcck":5.29,"Umsatz":1777.44},{"Produkt_ID":6,"Verkaufte Menge":399,"Produkt_Name":"Reis-fit Langkorn","Preis pro St\u00fcck":2.29,"Umsatz":913.71},{"Produkt_ID":21,"Verkaufte Menge":320,"Produkt_Name":"Red Bull Energy Drink 250ml","Preis pro St\u00fcck":1.49,"Umsatz":476.8},{"Produkt_ID":25,"Verkaufte Menge":313,"Produkt_Name":"Three Sixty Vodka 0,7L","Preis pro St\u00fcck":14.49,"Umsatz":4535.37},{"Produkt_ID":37,"Verkaufte Menge":418,"Produkt_Name":"Ovomaltine Crunchy Cream 380G","Preis pro St\u00fcck":4.79,"Umsatz":2002.22},{"Produkt_ID":39,"Verkaufte Menge":429,"Produkt_Name":"Milka Haselnusscreme 350G","Preis pro St\u00fcck":3.29,"Umsatz":1411.41},{"Produkt_ID":4,"Verkaufte Menge":298,"Produkt_Name":"Spaetzle 500g","Preis pro St\u00fcck":1.59,"Umsatz":473.82},{"Produkt_ID":1,"Verkaufte Menge":421,"Produkt_Name":"Nutella 450G","Preis pro St\u00fcck":3.49,"Umsatz":1469.29},{"Produkt_ID":3,"Verkaufte Menge":279,"Produkt_Name":"Tomatenmark","Preis pro St\u00fcck":1.09,"Umsatz":304.11},{"Produkt_ID":16,"Verkaufte Menge":393,"Produkt_Name":"Funny-Frisch Chipsfrisch Ungarisch 150G","Preis pro St\u00fcck":2.29,"Umsatz":899.97},{"Produkt_ID":31,"Verkaufte Menge":299,"Produkt_Name":"Erdinger Alkoholfrei 0,5L","Preis pro St\u00fcck":1.19,"Umsatz":355.81},{"Produkt_ID":19,"Verkaufte Menge":379,"Produkt_Name":"Paulanger Spezi 0,33L","Preis pro St\u00fcck":0.89,"Umsatz":337.31},{"Produkt_ID":2,"Verkaufte Menge":359,"Produkt_Name":"Gouda jung","Preis pro St\u00fcck":1.79,"Umsatz":642.61},{"Produkt_ID":7,"Verkaufte Menge":470,"Produkt_Name":"Choco Fresh 4+1","Preis pro St\u00fcck":1.19,"Umsatz":559.3},{"Produkt_ID":15,"Verkaufte Menge":335,"Produkt_Name":"Chio Tortillas Wild Paprika 110G","Preis pro St\u00fcck":1.99,"Umsatz":666.65},{"Produkt_ID":8,"Verkaufte Menge":154,"Produkt_Name":"Weizentoast 500g","Preis pro St\u00fcck":0.99,"Umsatz":152.46},{"Produkt_ID":12,"Verkaufte Menge":323,"Produkt_Name":"Prinzen Rolle Schoko 400G","Preis pro St\u00fcck":2.49,"Umsatz":804.27},{"Produkt_ID":34,"Verkaufte Menge":315,"Produkt_Name":"Oreo O's Cereal 350G","Preis pro St\u00fcck":3.99,"Umsatz":1256.85},{"Produkt_ID":20,"Verkaufte Menge":395,"Produkt_Name":"Capri-Sun Multivitamin 10x 0,2L","Preis pro St\u00fcck":4.49,"Umsatz":1773.55},{"Produkt_ID":10,"Verkaufte Menge":360,"Produkt_Name":"Kinder Maxi King","Preis pro St\u00fcck":2.38,"Umsatz":856.8},{"Produkt_ID":36,"Verkaufte Menge":394,"Produkt_Name":"Koelln Muesli Knusper Schoko & Keks 500G","Preis pro St\u00fcck":3.89,"Umsatz":1532.66},{"Produkt_ID":23,"Verkaufte Menge":267,"Produkt_Name":"Booster Original Energy Drink 0,33L","Preis pro St\u00fcck":0.79,"Umsatz":210.93},{"Produkt_ID":38,"Verkaufte Menge":367,"Produkt_Name":"Lotus Biscoff Brotaufstrich 400G","Preis pro St\u00fcck":3.79,"Umsatz":1390.93},{"Produkt_ID":30,"Verkaufte Menge":301,"Produkt_Name":"Krombacher Pils 0,5L","Preis pro St\u00fcck":0.99,"Umsatz":297.99},{"Produkt_ID":13,"Verkaufte Menge":366,"Produkt_Name":"Fuze Tea Lemon 0,4L","Preis pro St\u00fcck":1.29,"Umsatz":472.14},{"Produkt_ID":35,"Verkaufte Menge":425,"Produkt_Name":"Weetabix Minis Schokolade 500G","Preis pro St\u00fcck":4.49,"Umsatz":1908.25},{"Produkt_ID":28,"Verkaufte Menge":268,"Produkt_Name":"Jacobs Kroenung Kaffee gemahlen 500G","Preis pro St\u00fcck":7.99,"Umsatz":2141.32},{"Produkt_ID":14,"Verkaufte Menge":317,"Produkt_Name":"Fuze Tea Peach 0,4L","Preis pro St\u00fcck":1.29,"Umsatz":408.93},{"Produkt_ID":29,"Verkaufte Menge":294,"Produkt_Name":"Becks Pils 0,5L","Preis pro St\u00fcck":1.19,"Umsatz":349.86},{"Produkt_ID":27,"Verkaufte Menge":357,"Produkt_Name":"Lavazza Caffe Crema Classico Bohne 1KG","Preis pro St\u00fcck":16.99,"Umsatz":6065.43}]